yascp/__init__.py
yascp/__main__.py
yascp/parser.py
yascp/yascp_parser.py
yascp-0.3.2.data/scripts/yascp_parser.py
yascp-0.3.2.dist-info/LICENSE.txt
yascp-0.3.2.dist-info/METADATA
yascp-0.3.2.dist-info/WHEEL
yascp-0.3.2.dist-info/top_level.txt
yascp-0.3.2.dist-info/zip-safe
yascp-0.3.2.dist-info/RECORD
