Metadata-Version: 2.1
Name: yascp
Version: 0.3.2
Summary: Yet Another Simple Configuration Parser for       INI-style configuration files.
Home-page: https://pypi.python.org/pypi/yascp/
Author: Miroslaw Janiewicz
Author-email: miroslaw.janiewicz@gmail.com
License: MIT
Keywords: configuration,parse,parser,ini,yascp
Platform: UNKNOWN
Classifier: Development Status :: 4 - Beta
Classifier: Environment :: Console
License-File: LICENSE.txt
Requires-Dist: future
